[{
  "name": "bench_press",
  "weight": 1,
  "activations": [
    {
      "muscle": "middle_chest",
      "intensity": 10
    },
    {
      "muscle": "triceps",
      "intensity": 5
    }
  ],
  "seconds": 5,
  "sets": [3, 4, 5],
  "reps": [6, 8, 10],
  "tags": ["big_three"]
}, {
  "name": "incline_bench_press",
  "weight": 1,
  "activations": [
    {
      "muscle": "upper_chest",
      "intensity": 10
    },
    {
      "muscle": "triceps",
      "intensity": 5
    }
  ],
  "seconds": 5,
  "sets": [3, 4, 5],
  "reps": [6, 8, 10],
  "tags": ["big_three"]
}, {
  "name": "dumbbell_fly",
  "weight": 1,
  "activations": [
    {
      "muscle": "middle_chest",
      "intensity": 6
    }
  ],
  "seconds": 5,
  "sets": [3, 4, 5],
  "reps": [6, 8, 10],
  "tags": ["standard"]
}, {
  "name": "close_grip_bench_press",
  "weight": 1,
  "activations": [
    {
      "muscle": "triceps",
      "intensity": 8
    },
    {
      "muscle": "middle_chest",
      "intensity": 4
    }
  ],
  "seconds": 5,
  "sets": [3, 4, 5],
  "reps": [6, 8, 10],
  "tags": ["standard"]
}, {
  "name": "push_up",
  "weight": 1,
  "activations": [
    {
      "muscle": "middle_chest",
      "intensity": 3
    },
    {
      "muscle": "triceps",
      "intensity": 2
    }
  ],
  "seconds": 1,
  "sets": [3, 4, 5],
  "reps": [10, 15, 20],
  "tags": ["bodyweight"],
  "supersets": [{
     "exercise": "sit_up",
     "weight": 1
  }]
}, {
  "name": "sit_up",
  "weight": 1,
  "activations": [{
    "muscle": "abs",
    "intensity": 2
  }],
  "seconds": 2,
  "sets": [3, 4, 5],
  "reps": [10, 15, 20],
  "tags": ["bodyweight"]
}]
